LICENSE
MANIFEST.in
README.md
setup.py
apimaticcalculatorpythonv1/__init__.py
apimaticcalculatorpythonv1/api_helper.py
apimaticcalculatorpythonv1/apimaticcalculatorpythonv1_client.py
apimaticcalculatorpythonv1/configuration.py
apimaticcalculatorpythonv1/decorators.py
apimaticcalculatorpythonv1.egg-info/PKG-INFO
apimaticcalculatorpythonv1.egg-info/SOURCES.txt
apimaticcalculatorpythonv1.egg-info/dependency_links.txt
apimaticcalculatorpythonv1.egg-info/requires.txt
apimaticcalculatorpythonv1.egg-info/top_level.txt
apimaticcalculatorpythonv1/controllers/__init__.py
apimaticcalculatorpythonv1/controllers/base_controller.py
apimaticcalculatorpythonv1/controllers/calculator_e_ps.py
apimaticcalculatorpythonv1/exceptions/__init__.py
apimaticcalculatorpythonv1/exceptions/api_exception.py
apimaticcalculatorpythonv1/http/__init__.py
apimaticcalculatorpythonv1/http/http_call_back.py
apimaticcalculatorpythonv1/http/http_client.py
apimaticcalculatorpythonv1/http/http_context.py
apimaticcalculatorpythonv1/http/http_method_enum.py
apimaticcalculatorpythonv1/http/http_request.py
apimaticcalculatorpythonv1/http/http_response.py
apimaticcalculatorpythonv1/http/requests_client.py
apimaticcalculatorpythonv1/models/__init__.py
apimaticcalculatorpythonv1/models/operation_type.py
tests/__init__.py
tests/http_response_catcher.py
tests/test_helper.py
tests/controllers/__init__.py
tests/controllers/controller_test_base.py
tests/controllers/test_calculator_e_ps.py